reverse_geocode/__init__.py
reverse_geocode-1.6.3.data/data/reverse_geocode/countries.csv
reverse_geocode-1.6.3.data/data/reverse_geocode/geocode.json
reverse_geocode-1.6.3.dist-info/METADATA
reverse_geocode-1.6.3.dist-info/WHEEL
reverse_geocode-1.6.3.dist-info/top_level.txt
reverse_geocode-1.6.3.dist-info/RECORD
