Metadata-Version: 2.1
Name: reverse_geocode
Version: 1.6.3
Summary: Reverse geocode the given latitude / longitude
Home-page: https://github.com/richardpenman/reverse_geocode/
Author: Richard Penman
Author-email: richard.penman@gmail.com
License: lgpl
Classifier: Environment :: Web Environment
Classifier: Intended Audience :: Developers
Classifier: License :: OSI Approved :: GNU Library or Lesser General Public License (LGPL)
Classifier: Operating System :: OS Independent
Classifier: Programming Language :: Python
Classifier: Programming Language :: Python :: 3
Requires-Dist: numpy
Requires-Dist: scipy
